odoo/addons/website_google_tag_manager/README.rst
odoo/addons/website_google_tag_manager/__init__.py
odoo/addons/website_google_tag_manager/__manifest__.py
odoo/addons/website_google_tag_manager/i18n/af.po
odoo/addons/website_google_tag_manager/i18n/ar.po
odoo/addons/website_google_tag_manager/i18n/bg.po
odoo/addons/website_google_tag_manager/i18n/bs.po
odoo/addons/website_google_tag_manager/i18n/ca.po
odoo/addons/website_google_tag_manager/i18n/cs.po
odoo/addons/website_google_tag_manager/i18n/da.po
odoo/addons/website_google_tag_manager/i18n/de.po
odoo/addons/website_google_tag_manager/i18n/el.po
odoo/addons/website_google_tag_manager/i18n/el_GR.po
odoo/addons/website_google_tag_manager/i18n/en_GB.po
odoo/addons/website_google_tag_manager/i18n/es.po
odoo/addons/website_google_tag_manager/i18n/es_AR.po
odoo/addons/website_google_tag_manager/i18n/es_CL.po
odoo/addons/website_google_tag_manager/i18n/es_CO.po
odoo/addons/website_google_tag_manager/i18n/es_CR.po
odoo/addons/website_google_tag_manager/i18n/es_DO.po
odoo/addons/website_google_tag_manager/i18n/es_EC.po
odoo/addons/website_google_tag_manager/i18n/es_MX.po
odoo/addons/website_google_tag_manager/i18n/es_PE.po
odoo/addons/website_google_tag_manager/i18n/et.po
odoo/addons/website_google_tag_manager/i18n/eu.po
odoo/addons/website_google_tag_manager/i18n/fa.po
odoo/addons/website_google_tag_manager/i18n/fi.po
odoo/addons/website_google_tag_manager/i18n/fr.po
odoo/addons/website_google_tag_manager/i18n/fr_FR.po
odoo/addons/website_google_tag_manager/i18n/gl.po
odoo/addons/website_google_tag_manager/i18n/he.po
odoo/addons/website_google_tag_manager/i18n/hr.po
odoo/addons/website_google_tag_manager/i18n/hr_HR.po
odoo/addons/website_google_tag_manager/i18n/hu.po
odoo/addons/website_google_tag_manager/i18n/id.po
odoo/addons/website_google_tag_manager/i18n/it.po
odoo/addons/website_google_tag_manager/i18n/ja.po
odoo/addons/website_google_tag_manager/i18n/ka.po
odoo/addons/website_google_tag_manager/i18n/kab.po
odoo14_addon_website_google_tag_manager-14.0.1.0.1.dev12.dist-info/METADATA
odoo14_addon_website_google_tag_manager-14.0.1.0.1.dev12.dist-info/WHEEL
odoo14_addon_website_google_tag_manager-14.0.1.0.1.dev12.dist-info/top_level.txt
odoo14_addon_website_google_tag_manager-14.0.1.0.1.dev12.dist-info/RECORD
